LICENSE
kraken_spot/__init__.py
kraken_spot/auth.py
kraken_spot/client.py
kraken_spot/errors.py
kraken_spot/http.py
kraken_spot/private.py
kraken_spot/public.py
kraken_spot-1.0.0.dist-info/LICENSE
kraken_spot-1.0.0.dist-info/WHEEL
kraken_spot-1.0.0.dist-info/METADATA
kraken_spot-1.0.0.dist-info/RECORD
