Metadata-Version: 2.1
Name: kraken-spot
Version: 1.0.0
Summary: A library for interacting with the Kraken Spot API
Home-page: https://github.com/kevbradwick/kraken-spot
License: MIT
Keywords: kraken,crypto
Author: Kevin Bradwick
Author-email: kevinbradwick@gmail.com
Requires-Python: >=3.7,<4.0
Classifier: License :: OSI Approved :: MIT License
Classifier: Programming Language :: Python :: 3
Classifier: Programming Language :: Python :: 3.10
Classifier: Programming Language :: Python :: 3.7
Classifier: Programming Language :: Python :: 3.8
Classifier: Programming Language :: Python :: 3.9
Requires-Dist: requests (>=2.28.1,<3.0.0)
Project-URL: Repository, https://github.com/kevbradwick/kraken-spot
